maesters_of_clim/__init__.py
maesters_of_clim/analysis/__init__.py
maesters_of_clim/config/__init__.py
maesters_of_clim/config/index_forecast.toml
maesters_of_clim/config/index_history.toml
maesters_of_clim/fetcher/__init__.py
maesters_of_clim/fetcher/iri.py
maesters_of_clim/fetcher/jamstec.py
maesters_of_clim/fetcher/ncei.py
maesters_of_clim/fetcher/psl.py
maesters_of_clim/fetcher/rda.py
maesters_of_clim/utils/__init__.py
maesters_clim-0.0.4.dist-info/LICENSE
maesters_clim-0.0.4.dist-info/METADATA
maesters_clim-0.0.4.dist-info/WHEEL
maesters_clim-0.0.4.dist-info/top_level.txt
maesters_clim-0.0.4.dist-info/RECORD
