Metadata-Version: 2.1
Name: maesters-clim
Version: 0.0.4
Summary: Maesters-of-Clim tempt to help retriving climate data (climate index, reanalysis) from the main-stream climate insitution (like IRI, PSL, NCEI, RDA).
Home-page: https://github.com/blizhan/maesters-of-clim
Author: blizhan
Author-email: blizhan@icloud.com
Classifier: Programming Language :: Python :: 3
Requires-Python: >=3.6
License-File: LICENSE
Requires-Dist: toml
Requires-Dist: requests
Requires-Dist: pandas
Requires-Dist: numpy
Requires-Dist: beautifulsoup4
Requires-Dist: retrying
